modulos/__init__.py
modulos/modulos.py
modulos-0.2.0.dist-info/LICENSE
modulos-0.2.0.dist-info/METADATA
modulos-0.2.0.dist-info/WHEEL
modulos-0.2.0.dist-info/top_level.txt
modulos-0.2.0.dist-info/RECORD
