Metadata-Version: 2.1
Name: modulos
Version: 0.2.0
Summary: Simple python library for modulo operations
Author: Alexandre Chaminas
License: MIT
Project-URL: Homepage, https://github.com/samhanic/modulos
Platform: unix
Platform: linux
Platform: osx
Platform: cygwin
Platform: win32
Classifier: License :: OSI Approved :: MIT License
Classifier: Programming Language :: Python :: 3
Classifier: Programming Language :: Python :: 3 :: Only
Classifier: Programming Language :: Python :: 3.5
Classifier: Programming Language :: Python :: 3.6
Classifier: Programming Language :: Python :: 3.7
Classifier: Programming Language :: Python :: 3.8
Classifier: Programming Language :: Python :: 3.9
Classifier: Programming Language :: Python :: 3.10
Requires-Python: >=3.5
Provides-Extra: testing
License-File: LICENSE
